sicli/__about__.py
sicli/__init__.py
sicli/argument.py
sicli/exceptions.py
sicli/main.py
sicli/types.py
sicli/utils.py
sicli_cli-0.5.0.dist-info/METADATA
sicli_cli-0.5.0.dist-info/WHEEL
sicli_cli-0.5.0.dist-info/licenses/LICENSE
sicli_cli-0.5.0.dist-info/RECORD
