Metadata-Version: 2.1
Name: sicli-cli
Version: 0.5.0
Summary: Build simple command line tools easily and declaratively
Project-URL: Documentation, https://github.com/unknown/sicli#readme
Project-URL: Issues, https://github.com/immanelg/sicli/issues
Project-URL: Source, https://github.com/immanelg/sicli
Author: immanelg
License-Expression: MIT
License-File: LICENSE
Classifier: Development Status :: 4 - Beta
Classifier: Programming Language :: Python
Classifier: Programming Language :: Python :: 3.10
Classifier: Programming Language :: Python :: 3.11
Classifier: Programming Language :: Python :: Implementation :: CPython
Requires-Python: >=3.7
